MANIFEST.in
README.rst
setup.cfg
setup.py
PyGitUpAll/__init__.py
PyGitUpAll/gitupall.py
PyGitUpAll/project.py
PyGitUpAll/utils.py
git_up_all.egg-info/PKG-INFO
git_up_all.egg-info/SOURCES.txt
git_up_all.egg-info/dependency_links.txt
git_up_all.egg-info/entry_points.txt
git_up_all.egg-info/not-zip-safe
git_up_all.egg-info/requires.txt
git_up_all.egg-info/top_level.txt