Metadata-Version: 1.1
Name: git-up-all
Version: 0.3.1.0
Summary: Run git-up trough a json list of repos
Home-page: https://github.com/jimmykane/PyGitUpAll
Author: Dimitrios Kanellopoulos
Author-email: jimmykane9@gmail.com
License: GPLv3
Download-URL: https://github.com/jimmykane/PyGitUpAll/tarball/master/0.3.1.0
Keywords: git git-up git-up-all
Platform: UNKNOWN
Classifier: Development Status :: 4 - Beta
Classifier: Environment :: Console
Classifier: Intended Audience :: Developers
Classifier: License :: OSI Approved :: GNU General Public License v3 or later (GPLv3+)
Classifier: Topic :: Software Development :: Version Control
Classifier: Topic :: Utilities
